<?xml version="1.0" encoding="UTF-8" ?>

<DialoguesCollection>
	<Dialogues>

    <!-- Parte 1 -->
	  <Dialog>
			<Id>primeiroDialogo</Id>
			<Message>José as dores estão aumentando...!!!</Message>
			<IdScene>rodoviariaCidadeInterior</IdScene>
			<IdCharacter>mariaGravida</IdCharacter>
	    <NextDialog>
	      <value>dialogoRodoviaria</value>
	    </NextDialog>
		</Dialog>

	  <Dialog>
	    <Id>dialogoRodoviaria</Id>
	    <Message>Respire fundo meu amor...</Message>
	    <IdScene>rodoviariaCidadeInterior</IdScene>
	    <IdCharacter>jose</IdCharacter>
      <NextDialog>
        <value>dialogoRodoviaria1</value>
      </NextDialog>
	  </Dialog>

	  <Dialog>
	    <Id>dialogoRodoviaria1</Id>
	    <Message>Acho que não vai dar tempo de chegar lá em Curitiba, o que vamos fazer?</Message>
	    <NextDialog>
	      <value>dialogoRodoviaria2</value>
	    </NextDialog>
	    <IdScene>rodoviariaCidadeInterior</IdScene>
	    <IdCharacter>mariaGravida</IdCharacter>
	  </Dialog>

	  <Dialog>
	    <Id>dialogoRodoviaria2</Id>
	    <Message>E agora, vou procurar uma carona para nós, ou arrisco esperar o ônibus?</Message>
	    <IdScene>rodoviariaCidadeInterior</IdScene>
	    <IdCharacter>jose</IdCharacter>
	    <NextDialog>
	      <value>dialogoRodoviariaOp1</value>
	      <value>dialogoRodoviariaOp2</value>
	    </NextDialog>
	  </Dialog>
    
	  <Dialog>
	    <Id>dialogoRodoviariaOp1</Id>
	    <Message>Procurar carona!</Message>
	    <NextDialog>
	      <value>procurarCarona</value>
	    </NextDialog>
	  </Dialog>
    
	  <Dialog>
	    <Id>dialogoRodoviariaOp2</Id>
	    <Message>Esperar ônibus!</Message>
	    <NextDialog>
	      <value>dialogoRodoviaria3</value>
	    </NextDialog>
	  </Dialog>
    
	  <Dialog>
	    <Id>dialogoRodoviaria3</Id>
	    <Message>Amooor!!! Aah!! ESTOUROU A BOLSA!!!</Message>
	    <NextDialog>
	      <value>dialogoRodoviaria4</value>
	    </NextDialog>
	    <IdScene>rodoviariaCidadeInterior</IdScene>
	    <IdCharacter>mariaGravida</IdCharacter>
	  </Dialog>
 
	  <Dialog>
	    <Id>dialogoRodoviaria4</Id>
	    <Message></Message>
	    <IdScene>rodoviariaCidadeInterior</IdScene>
	    <IdCharacter>jose</IdCharacter>
	    <NextDialog>
	      <value>dialogoRodoviariaOp3</value>
	      <value>dialogoRodoviariaOp4</value>
	    </NextDialog>
	  </Dialog>
    
	  <Dialog>
	    <Id>dialogoRodoviariaOp3</Id>
	    <Message>Ficar ao lado de sua esposa auxiliando.</Message>
	    <NextDialog>
	      <value>auxiliarEsposa</value>
	    </NextDialog>
	  </Dialog>
    
	  <Dialog>
	    <Id>dialogoRodoviariaOp4</Id>
	    <Message>Buscar alguém que possa ajudar.</Message>
	    <NextDialog>
	      <value>buscarAjuda</value>
	    </NextDialog>
	  </Dialog>
    
	  <Dialog>
	    <Id>auxiliarEsposa</Id>
	    <Message>Maria?!?! POR FAVOR ALGUÉM NOS AJUDE!!!</Message>
	    <NextDialog>
	      <value>dialogoRodoviaria5</value>
	    </NextDialog>
	    <IdScene>rodoviariaCidadeInterior</IdScene>
	    <IdCharacter>jose</IdCharacter>
	  </Dialog>
    
	  <Dialog>
	    <Id>dialogoRodoviaria5</Id>
	    <Message>Sou enfermeiro, posso ajudar!</Message>
	    <IdScene>rodoviariaCidadeInterior</IdScene>
	    <IdCharacter>enfermeiroRodoviaria</IdCharacter>
      <NextDialog>
        <value>dialogoRodoviaria6</value>
      </NextDialog>
	  </Dialog>

    <Dialog>
      <Id>dialogoRodoviaria6</Id>
      <Message>Finalmente...</Message>
      <IdScene>rodoviariaCidadeInterior</IdScene>
      <IdCharacter>mariaBebe</IdCharacter>
      <NextDialog>
        <value>dialogoRodoviaria7</value>
      </NextDialog>
    </Dialog>
    
    <Dialog>
      <Id>dialogoRodoviaria7</Id>
      <Message>Você preferiu ficar ao lado de sua esposa. As pessoas que estavam na rodoviária correram para perto de vocês, algumas curiosas, outras para admirar o bebê que acabara de nascer. Melchior, que estava nos bancos ao lado, ajudou dando o cobertor que levava para a viagem para cobrir o bebê. Gaspar que esperava o ônibus para ir para Curitiba era também um enfermeiro especializado em obstetrícia. Baltazar o motorista do ônibus acabou ficando encarregado de disponibilizar os materiais para o parto do menino Jesus. </Message>
      <IdScene>presepioRodoviaria</IdScene>
    </Dialog>
    
     <Dialog>
      <Id>buscarAjuda</Id>
      <Message>Sou enfermeiro, posso ajudar por enquanto, mas, precisamos chamar uma ambulância com urgência.</Message>
      <IdScene>rodoviariaCidadeInterior</IdScene>
      <IdCharacter>enfermeiroRodoviaria</IdCharacter>
      <NextDialog>
        <value>finalDialogoHospital</value>
      </NextDialog>
    </Dialog>   

      
    <Dialog>
      <Id>finalDialogoHospital</Id>
      <Message>Quando vocês chegaram no hospital o médico Gaspar já estava com tudo pronto esperando por Maria. Melchior, havia ligado para seu amigo e lhe pedido para agilizar o processo. Deu tudo certo, seu filho é lindo e emana saúde. Com alegria, todos os que ajudaram, vem visitar o bebê</Message>
      <IdScene>quartoHospital</IdScene>
    </Dialog>  
	  <!-- Parte 2 -->


    <Dialog>
      <Id>procurarCarona</Id>
      <Message>Não posso deixar uma mulher grávida esperando ônibus, eu levo vocês.</Message>
      <IdScene>rodoviariaCidadeInterior</IdScene>
      <IdCharacter>motoristaBaltazar</IdCharacter>
      <NextDialog>
        <value>dialogoCarona0</value>
      </NextDialog>
    </Dialog>

    <Dialog>
      <Id>dialogoCarona0</Id>
      <Message>Foi um caminho tenso Maria estava suando frio aguentava sua dor em silêncio para não preocupar você e o motorista.</Message>
      <IdScene>estradaFazenda2</IdScene>
      <NextDialog>
        <value>dialogoCarona1</value>
      </NextDialog>
    </Dialog>
    
    <Dialog>
      <Id>dialogoCarona1</Id>
      <Message>José, grrrrr!! Está quase na hora! </Message>
      <IdScene>estradaFazenda2</IdScene>
      <IdCharacter>mariaGravida</IdCharacter>
      <NextDialog>
        <value>dialogoCarona2</value>
      </NextDialog>
    </Dialog>

    <Dialog>
      <Id>dialogoCarona2</Id>
      <Message>Você acha que dá tempo de chegarmos?</Message>
      <IdScene>estradaFazenda2</IdScene>
      <IdCharacter>jose</IdCharacter>
      <NextDialog>
        <value>dialogoCarona3</value>
      </NextDialog>
    </Dialog>

    <Dialog>
      <Id>dialogoCarona3</Id>
      <Message>Não falta muito não, José.</Message>
      <IdScene>estradaFazenda2</IdScene>
      <IdCharacter>motoristaBaltazar</IdCharacter>
      <NextDialog>
        <value>dialogoCarona4</value>
      </NextDialog>
    </Dialog>

    <Dialog>
      <Id>dialogoCarona4</Id>
      <Message>Não sei meu amor. Eu acho que aguento.</Message>
      <IdScene>estradaFazenda2</IdScene>
      <IdCharacter>mariaGravida</IdCharacter>
      <NextDialog>
        <value>dialogoCarona5</value>
      </NextDialog>
    </Dialog>
    
    <Dialog>
      <Id>dialogoCarona5</Id>
      <Message>Você percebe agora que só tem duas opções, e deve escolher o mais rápido possível.</Message>
      <IdScene>estradaFazenda</IdScene>
      <NextDialog>
        <value>dialogoCaronaOp1</value>
        <value>dialogoCaronaOp2</value>
      </NextDialog>
    </Dialog>
    
    <Dialog>
      <Id>dialogoCaronaOp1</Id>
      <Message>Pedir para que o motorista pare na estrada.</Message>
      <NextDialog>
        <value>finalDialogoCarona</value>
      </NextDialog>
    </Dialog>

    <Dialog>
      <Id>dialogoCaronaOp2</Id>
      <Message>Tentar chegar em Curitiba.</Message>
      <NextDialog>
        <value>finalDialogoHospital</value>
      </NextDialog>
    </Dialog>

    <Dialog>
      <Id>finalDialogoCarona</Id>
      <Message>Você decidiu pedir para Baltazar parar pois tinha visto uma casa bem grande e bonita, a um minuto dali. Melchior, um fazendeiro que estava procurando uma ovelha perdida, viu o ônibus que acabou de parar em frente à sua casa, logo vai até lá para ver o que aconteceu</Message>
      <IdScene>estradaFazenda</IdScene>
      <NextDialog>
        <value>dialogoFazenda</value>
      </NextDialog>
    </Dialog>

    <Dialog>
      <Id>dialogoFazenda</Id>
      <Message>E aí amigo, aconteceu alguma coisa com o ônibus?</Message>
      <IdScene>estradaFazenda</IdScene>
      <IdCharacter>melchior</IdCharacter>
      <NextDialog>
        <value>dialogoFazenda1</value>
      </NextDialog>
    </Dialog>

    <Dialog>
      <Id>dialogoFazenda1</Id>
      <Message>Tem uma passageira que está com dores de parto e não temos como prosseguir viagem com ela assim.</Message>
      <IdScene>estradaFazenda</IdScene>
      <IdCharacter>motoristaBaltazar</IdCharacter>
      <NextDialog>
        <value>dialogoFazenda2</value>
      </NextDialog>
    </Dialog>

    <Dialog>
      <Id>dialogoFazenda2</Id>
      <Message>Minha casa é pequena, mas tem um espaço lá no alpendre, eles podem passar a noite aqui.</Message>
      <IdScene>estradaFazenda</IdScene>
      <IdCharacter>melchior</IdCharacter>
      <NextDialog>
        <value>dialogoFazenda3</value>
      </NextDialog>
    </Dialog>

    <Dialog>
      <Id>dialogoFazenda3</Id>
      <Message>Agradeço sua ajuda, aceitamos sim.</Message>
      <IdScene>estradaFazenda</IdScene>
      <IdCharacter>jose</IdCharacter>
      <NextDialog>
        <value>dialogoFazenda4</value>
      </NextDialog>
    </Dialog>

    <Dialog>
      <Id>dialogoFazenda4</Id>
      <Message>Joséeeeeee, a bolsa estourou!</Message>
      <IdScene>estradaFazenda</IdScene>
      <IdCharacter>mariaGravida</IdCharacter>
      <NextDialog>
        <value>dialogoFazenda5</value>
      </NextDialog>
    </Dialog>
    
    <Dialog>
      <Id>dialogoFazenda5</Id>
      <Message>Gaspar, filho de Melchior que o estava ajudando com a ovelha, ao ver Maria logo corre para ajudar José levá-la para o alpendre.</Message>
      <IdScene>estradaFazenda</IdScene>
      <NextDialog>
        <value>dialogoFazenda6</value>
      </NextDialog>
    </Dialog>
    
    <Dialog>
      <Id>dialogoFazenda6</Id>
      <Message>deixe-me ajudá-los.</Message>
      <IdScene>estradaFazenda</IdScene>
      <IdCharacter>gaspar</IdCharacter>
      <NextDialog>
        <value>finalDialogoFazenda</value>
      </NextDialog>
    </Dialog>

    <Dialog>
      <Id>finalDialogoFazenda</Id>
      <Message>Melchior e Gaspar tinham conhecimento de parto animal, o que ajudou a facilitar o parto de Maria. Logo se escuta o choro do bebê, naquela noite veio ao mundo em meio aos animais da fazenda. Todos da casa ficam em volta para admirar o bebê que acabara de nascer. Melchior: Maria, arrumei a manjedoura para colocar o bebê.</Message>
      <IdScene></IdScene>
    </Dialog>
    

	</Dialogues>
</DialoguesCollection>